{
  "timestamp": "2026-06-03T14:38:53.627239",
  "config": {
    "depth": "balanced",
    "thresholds": {
      "full": 0.75,
      "partial": 0.65,
      "minimum": 0.0
    }
  },
  "recommendations": [
    {
      "vet_units": [
        "ICTNWK544: Design and implement a security perimeter for ICT networks",
        "ICTSAS440: Monitor and administer security of ICT systems",
        "ICTNWK546: Manage network security",
        "ICTNWK537: Implement secure encryption technologies"
      ],
      "uni_course": "CSE1CPR",
      "score": 0.7640157105790244,
      "type": "partial",
      "confidence": 0.8858333333333333,
      "evidence": [
        "Skill coverage: 74.8%",
        "Match quality: 68.3%",
        "Level alignment: 80.0%",
        "Context alignment: 80.0%",
        "Direct matching: 11 exact matches",
        "12 skill clusters matched",
        "Course level: University_Year_1",
        "Rationale: The VET units demonstrate strong alignment with the majority of core practical skills required for the Cybersecurity in Practice subject, justifying a partial credit transfer. However, the overall coverage falls short of the threshold for full recognition, indicating the need to address residual competency gaps."
      ],
      "gaps": []
    },
    {
      "vet_units": [
        "ICTNWK538: Install and maintain valid authentication processes",
        "ICTNWK544: Design and implement a security perimeter for ICT networks",
        "ICTICT426: Identify and evaluate emerging technologies and practices",
        "ICTNWK435: Create secure virtual private networks",
        "ICTSAS440: Monitor and administer security of ICT systems",
        "ICTNWK546: Manage network security",
        "ICTNWK537: Implement secure encryption technologies"
      ],
      "uni_course": "CSE1ICB",
      "score": 0.7337186883264117,
      "type": "partial",
      "confidence": 0.8570833333333333,
      "evidence": [
        "Skill coverage: 70.6%",
        "Match quality: 66.2%",
        "Level alignment: 76.7%",
        "Context alignment: 78.0%",
        "Direct matching: 11 exact matches",
        "15 skill clusters matched",
        "Course level: University_Year_1",
        "Rationale: The VET qualification demonstrates strong alignment with the majority of core cybersecurity competencies required by the university subject, but it does not cover several key areas such as digital forensics, information security management and vulnerability mitigation, warranting a partial credit transfer."
      ],
      "gaps": []
    },
    {
      "vet_units": [
        "ICTNWK538: Install and maintain valid authentication processes",
        "ICTCLD301: Evaluate characteristics of cloud computing solutions and services",
        "ICTICT443: Work collaboratively in the ICT industry",
        "ICTICT426: Identify and evaluate emerging technologies and practices",
        "ICTSAS526: Review and update disaster recovery and contingency plans",
        "ICTNWK422: Install and manage servers",
        "ICTNWK537: Implement secure encryption technologies"
      ],
      "uni_course": "CSE1IIT",
      "score": 0.7046619136973665,
      "type": "partial",
      "confidence": 0.8494444444444444,
      "evidence": [
        "Skill coverage: 69.2%",
        "Match quality: 61.4%",
        "Level alignment: 72.9%",
        "Context alignment: 72.5%",
        "Direct matching: 3 exact matches",
        "12 skill clusters matched",
        "Course level: University_Year_1",
        "Rationale: The VET qualification demonstrates substantial overlap with the university unit, covering core analytical and problem\u2011solving competencies, but it does not address several foundational technical topics required for full credit. Consequently a partial credit recommendation is appropriate."
      ],
      "gaps": []
    },
    {
      "vet_units": [
        "ICTICT426: Identify and evaluate emerging technologies and practices",
        "ICTNWK538: Install and maintain valid authentication processes",
        "ICTNWK435: Create secure virtual private networks",
        "ICTNWK546: Manage network security"
      ],
      "uni_course": "CSE2WIN",
      "score": 0.6905341167167381,
      "type": "partial",
      "confidence": 0.8945000000000001,
      "evidence": [
        "Skill coverage: 59.8%",
        "Match quality: 72.3%",
        "Level alignment: 66.7%",
        "Context alignment: 75.8%",
        "Direct matching: 3 exact matches",
        "12 skill clusters matched",
        "Course level: University_Year_2",
        "Rationale: The VET qualification covers a substantial portion of the core security and authentication competencies required for the Wireless Network and Security unit, but it does not address specific wireless\u2011focused concepts such as CIA principles and signal impairment mitigation, necessitating partial credit."
      ],
      "gaps": []
    },
    {
      "vet_units": [
        "ICTSAS440: Monitor and administer security of ICT systems",
        "ICTPRG435: Write scripts for software applications",
        "ICTPRG434: Automate processes"
      ],
      "uni_course": "CSE1PE",
      "score": 0.6160935953258608,
      "type": "partial",
      "confidence": 0.917142857142857,
      "evidence": [
        "Skill coverage: 57.8%",
        "Match quality: 51.9%",
        "Level alignment: 63.6%",
        "Context alignment: 63.6%",
        "Direct matching: 6 exact matches",
        "11 skill clusters matched",
        "Course level: University_Year_1",
        "Rationale: The VET qualification demonstrates solid overlap with core programming and algorithmic concepts required for CSE1PE, justifying a partial credit transfer. However, several foundational university outcomes are not addressed, necessitating additional study."
      ],
      "gaps": []
    },
    {
      "vet_units": [
        "ICTNWK538: Install and maintain valid authentication processes",
        "ICTNWK537: Implement secure encryption technologies"
      ],
      "uni_course": "MAT1003",
      "score": 0.5335361511203979,
      "type": "partial",
      "confidence": 0.8770000000000001,
      "evidence": [
        "Skill coverage: 46.6%",
        "Match quality: 45.8%",
        "Level alignment: 55.6%",
        "Context alignment: 55.6%",
        "Direct matching: 5 exact matches",
        "9 skill clusters matched",
        "Course level: University_Year_1",
        "Rationale: The VET units demonstrate solid overlap with core cryptographic concepts, covering encryption standards and authentication processes, but several key university learning outcomes remain unmapped, justifying a partial credit transfer."
      ],
      "gaps": []
    },
    {
      "vet_units": [
        "ICTNWK538: Install and maintain valid authentication processes",
        "ICTCLD301: Evaluate characteristics of cloud computing solutions and services",
        "ICTSAS526: Review and update disaster recovery and contingency plans"
      ],
      "uni_course": "STA1DCT",
      "score": 0.5110759309669021,
      "type": "partial",
      "confidence": 0.8692857142857143,
      "evidence": [
        "Skill coverage: 40.7%",
        "Match quality: 47.6%",
        "Level alignment: 58.3%",
        "Context alignment: 48.3%",
        "Direct matching: 4 exact matches",
        "11 skill clusters matched",
        "Course level: University_Year_1",
        "Rationale: The VET qualification demonstrates solid overlap with core data interpretation and critical identification skills required by the university subject, justifying partial credit. However, key components such as probability concepts and evaluation of media\u2011derived data are not covered, limiting full recognition."
      ],
      "gaps": []
    },
    {
      "vet_units": [
        "ICTCLD301: Evaluate characteristics of cloud computing solutions and services",
        "ICTICT426: Identify and evaluate emerging technologies and practices",
        "ICTSAS440: Monitor and administer security of ICT systems",
        "ICTPRG434: Automate processes",
        "ICTNWK546: Manage network security"
      ],
      "uni_course": "CSE3PM",
      "score": 0.4948415018900847,
      "type": "partial",
      "confidence": 0.8987499999999999,
      "evidence": [
        "Skill coverage: 35.2%",
        "Match quality: 52.5%",
        "Level alignment: 44.2%",
        "Context alignment: 61.5%",
        "Direct matching: 1 exact matches",
        "13 skill clusters matched",
        "Course level: University_Year_3",
        "Rationale: The VET qualification demonstrates a strong direct match in risk management and several relevant partial overlaps, but it does not cover a number of core project management competencies required for full credit. Consequently, only partial credit is appropriate."
      ],
      "gaps": []
    },
    {
      "vet_units": [
        "ICTSAS526: Review and update disaster recovery and contingency plans",
        "ICTSAS440: Monitor and administer security of ICT systems",
        "ICTNWK546: Manage network security",
        "ICTNWK537: Implement secure encryption technologies"
      ],
      "uni_course": "CSE2SIA",
      "score": 0.42606646529391956,
      "type": "none",
      "confidence": 0.901875,
      "evidence": [
        "Skill coverage: 27.6%",
        "Match quality: 46.9%",
        "Level alignment: 40.0%",
        "Context alignment: 43.3%",
        "Direct matching: 3 exact matches",
        "12 skill clusters matched",
        "Course level: University_Year_2"
      ],
      "gaps": []
    },
    {
      "vet_units": [
        "ICTSAS440: Monitor and administer security of ICT systems",
        "ICTNWK546: Manage network security",
        "ICTNWK537: Implement secure encryption technologies"
      ],
      "uni_course": "CSE3NSW",
      "score": 0.41058861435784233,
      "type": "none",
      "confidence": 0.8950000000000001,
      "evidence": [
        "Skill coverage: 30.1%",
        "Match quality: 41.2%",
        "Level alignment: 33.3%",
        "Context alignment: 42.7%",
        "Direct matching: 2 exact matches",
        "13 skill clusters matched",
        "Course level: University_Year_3"
      ],
      "gaps": []
    },
    {
      "vet_units": [
        "ICTSAS440: Monitor and administer security of ICT systems",
        "ICTNWK546: Manage network security",
        "ICTPRG434: Automate processes"
      ],
      "uni_course": "CSE2HUM",
      "score": 0.3872095125503641,
      "type": "none",
      "confidence": 0.8914285714285715,
      "evidence": [
        "Skill coverage: 23.9%",
        "Match quality: 39.1%",
        "Level alignment: 35.0%",
        "Context alignment: 46.7%",
        "Direct matching: 2 exact matches",
        "15 skill clusters matched",
        "Course level: University_Year_2"
      ],
      "gaps": []
    },
    {
      "vet_units": [
        "ICTNWK544: Design and implement a security perimeter for ICT networks",
        "ICTSAS440: Monitor and administer security of ICT systems",
        "BSBINS401: Analyse and present research information",
        "ICTNWK546: Manage network security"
      ],
      "uni_course": "CSE3002",
      "score": 0.3527780875136612,
      "type": "none",
      "confidence": 0.887857142857143,
      "evidence": [
        "Skill coverage: 17.2%",
        "Match quality: 41.7%",
        "Level alignment: 31.7%",
        "Context alignment: 38.0%",
        "Direct matching: 2 exact matches",
        "14 skill clusters matched",
        "Course level: University_Year_3"
      ],
      "gaps": []
    },
    {
      "vet_units": [
        "ICTNWK435: Create secure virtual private networks",
        "ICTNWK422: Install and manage servers"
      ],
      "uni_course": "CSE3INE",
      "score": 0.34132566925104335,
      "type": "none",
      "confidence": 0.9135714285714288,
      "evidence": [
        "Skill coverage: 13.8%",
        "Match quality: 36.5%",
        "Level alignment: 35.0%",
        "Context alignment: 46.7%",
        "Direct matching: 0 exact matches",
        "13 skill clusters matched",
        "Course level: University_Year_3"
      ],
      "gaps": []
    },
    {
      "vet_units": [
        "ICTSAS440: Monitor and administer security of ICT systems",
        "ICTPRG434: Automate processes"
      ],
      "uni_course": "CSE1OOF",
      "score": 0.28914597274528614,
      "type": "none",
      "confidence": 0.9,
      "evidence": [
        "Skill coverage: 20.2%",
        "Match quality: 21.3%",
        "Level alignment: 25.0%",
        "Context alignment: 22.5%",
        "Direct matching: 1 exact matches",
        "12 skill clusters matched",
        "Course level: University_Year_1"
      ],
      "gaps": []
    },
    {
      "vet_units": [
        "ICTSAS440: Monitor and administer security of ICT systems",
        "ICTNWK546: Manage network security"
      ],
      "uni_course": "CSE3CFN",
      "score": 0.26399875107738713,
      "type": "none",
      "confidence": 0.895,
      "evidence": [
        "Skill coverage: 11.4%",
        "Match quality: 23.9%",
        "Level alignment: 22.5%",
        "Context alignment: 30.0%",
        "Direct matching: 0 exact matches",
        "10 skill clusters matched",
        "Course level: University_Year_3"
      ],
      "gaps": []
    },
    {
      "vet_units": [
        "ICTCLD301: Evaluate characteristics of cloud computing solutions and services",
        "ICTICT443: Work collaboratively in the ICT industry"
      ],
      "uni_course": "LTU0AIM",
      "score": 0.2441057973425798,
      "type": "none",
      "confidence": 0.8775,
      "evidence": [
        "Skill coverage: 17.3%",
        "Match quality: 14.3%",
        "Level alignment: 18.2%",
        "Context alignment: 18.2%",
        "Direct matching: 0 exact matches",
        "10 skill clusters matched",
        "Course level: University_Year_1"
      ],
      "gaps": []
    },
    {
      "vet_units": [
        "ICTNWK544: Design and implement a security perimeter for ICT networks",
        "ICTNWK422: Install and manage servers"
      ],
      "uni_course": "CSE2NEF",
      "score": 0.23620134286085764,
      "type": "none",
      "confidence": 0.915,
      "evidence": [
        "Skill coverage: 16.7%",
        "Match quality: 14.1%",
        "Level alignment: 14.6%",
        "Context alignment: 16.7%",
        "Direct matching: 2 exact matches",
        "11 skill clusters matched",
        "Course level: University_Year_1"
      ],
      "gaps": []
    },
    {
      "vet_units": [
        "BSBINS401: Analyse and present research information",
        "ICTNWK537: Implement secure encryption technologies"
      ],
      "uni_course": "LAW2CLP",
      "score": 0.18210803579401086,
      "type": "none",
      "confidence": 0.9,
      "evidence": [
        "Skill coverage: 7.8%",
        "Match quality: 11.0%",
        "Level alignment: 10.0%",
        "Context alignment: 13.3%",
        "Direct matching: 0 exact matches",
        "14 skill clusters matched",
        "Course level: University_Year_2"
      ],
      "gaps": []
    },
    {
      "vet_units": [
        "ICTSAS440: Monitor and administer security of ICT systems",
        "ICTPRG434: Automate processes"
      ],
      "uni_course": "CSE3PPE",
      "score": 0.17697546200840564,
      "type": "none",
      "confidence": 0.885,
      "evidence": [
        "Skill coverage: 6.8%",
        "Match quality: 10.9%",
        "Level alignment: 10.0%",
        "Context alignment: 13.3%",
        "Direct matching: 0 exact matches",
        "15 skill clusters matched",
        "Course level: University_Year_3"
      ],
      "gaps": []
    },
    {
      "vet_units": [
        "ICTNWK546: Manage network security"
      ],
      "uni_course": "CSE3BCC",
      "score": 0.1303175650790886,
      "type": "none",
      "confidence": 0.89,
      "evidence": [
        "Skill coverage: 2.3%",
        "Match quality: 6.0%",
        "Level alignment: 3.3%",
        "Context alignment: 6.7%",
        "Direct matching: 0 exact matches",
        "12 skill clusters matched",
        "Course level: University_Year_3"
      ],
      "gaps": []
    },
    {
      "vet_units": [],
      "uni_course": "ABS0WOM",
      "score": 0.05,
      "type": "none",
      "confidence": 0.0,
      "evidence": [
        "Skill coverage: 0.0%",
        "Match quality: 0.0%",
        "Level alignment: 0.0%",
        "Context alignment: 0.0%",
        "Direct matching: 0 exact matches",
        "15 skill clusters matched",
        "Course level: University_Year_1"
      ],
      "gaps": []
    }
  ]
}